og/__init__.py
og-0.0.5.dist-info/licenses/LICENSE
og-0.0.5.dist-info/METADATA
og-0.0.5.dist-info/WHEEL
og-0.0.5.dist-info/top_level.txt
og-0.0.5.dist-info/RECORD
