Metadata-Version: 2.4
Name: og
Version: 0.0.5
Summary: Frequent itemsets -- fp-tree naeseth
Home-page: https://github.com/t-c-w/og
Author: Thor Whalen
License: apache-2.0
Platform: any
License-File: LICENSE
Dynamic: license-file
